{"primaryContentSections":[{"content":[{"text":"Setup","level":2,"type":"heading","anchor":"Setup"},{"items":[{"content":[{"type":"paragraph","inlineContent":[{"text":"Version 4:","type":"text"}]}]}],"type":"unorderedList"},{"code":["dependencies: [","    .package(url: \"https:\/\/github.com\/expofp\/expofp-fplan-ios-spm\", from: \"4.9.4\"),","],","targets: [","    .target(","        name: \"MyApp\",","        dependencies: [","            .product(name: \"ExpoFpFplan\", package: \"expofp-fplan-ios-spm\"),","        ]","    ),","]"],"type":"codeListing","syntax":"swift"},{"code":["target 'MyApp' do","    pod 'ExpoFpFplan', '~> 4.9.4'","end"],"type":"codeListing","syntax":null},{"items":[{"content":[{"inlineContent":[{"type":"text","text":"Version 5:"}],"type":"paragraph"}]}],"type":"unorderedList"},{"code":["dependencies: [","    .package(url: \"https:\/\/github.com\/expofp\/expofp-sdk-ios\", from: \"5.3.0\"),","],","targets: [","    .target(","        name: \"MyApp\",","        dependencies: [","            .product(name: \"ExpoFP\", package: \"expofp-sdk-ios\"),","        ]","    ),","]"],"type":"codeListing","syntax":"swift"},{"code":["target 'MyApp' do","    pod 'ExpoFP', '~> 5.3.0'","end"],"type":"codeListing","syntax":null},{"text":"Import","level":2,"type":"heading","anchor":"Import"},{"items":[{"content":[{"type":"paragraph","inlineContent":[{"type":"text","text":"Version 4:"}]}]}],"type":"unorderedList"},{"code":["import ExpoFpFplan"],"type":"codeListing","syntax":"swift"},{"items":[{"content":[{"inlineContent":[{"type":"text","text":"Version 5:"}],"type":"paragraph"}]}],"type":"unorderedList"},{"code":["import ExpoFP"],"type":"codeListing","syntax":"swift"},{"text":"Initialization","level":2,"type":"heading","anchor":"Initialization"},{"text":"UIKit","level":3,"type":"heading","anchor":"UIKit"},{"items":[{"content":[{"type":"paragraph","inlineContent":[{"type":"text","text":"Version 4:"}]}]}],"type":"unorderedList"},{"code":["class YourViewController: UIViewController {","    var fplanUiView: UIFplanView!","","    override func loadView() {","        fplanUiView = UIFplanView()","        self.view = fplanUiView","    }","","    override func viewDidLoad() {","        super.viewDidLoad()","        fplanUiView.load(\"https:\/\/demo.expofp.com\")","    }","","    override func viewWillDisappear(_ animated: Bool) {","        fplanUiView.destoy()","    }","}"],"type":"codeListing","syntax":"swift"},{"items":[{"content":[{"inlineContent":[{"type":"text","text":"Version 5:"}],"type":"paragraph"}]}],"type":"unorderedList"},{"code":["let expoKey = \"demo\"","let presenter = ExpoFpPlan.createPlanPresenter(with: .expoKey(expoKey))","let planController = presenter.getViewController()","yourViewController.pushViewController(planController, animated: true)"],"type":"codeListing","syntax":"swift"},{"text":"SwiftUI","level":3,"type":"heading","anchor":"SwiftUI"},{"items":[{"content":[{"type":"paragraph","inlineContent":[{"type":"text","text":"Version 4:"}]}]}],"type":"unorderedList"},{"code":["var fplanView = FplanView()","","var body: some View {","    fplanView","        .onAppear {","            fplanView.load(\"https:\/\/demo.expofp.com\")","        }","        .onDisappear {","            fplanView.destoy()","        }","}"],"type":"codeListing","syntax":"swift"},{"items":[{"content":[{"type":"paragraph","inlineContent":[{"type":"text","text":"Version 5:"}]}]}],"type":"unorderedList"},{"code":["@StateObject var viewModel = YourViewModel(presenter: ExpoFpPlan.createPlanPresenter(with: .expoKey(\"demo\")))","","var body: some View {","    viewModel.presenter.getView()","}"],"type":"codeListing","syntax":"swift"},{"text":"Settings","level":2,"type":"heading","anchor":"Settings"},{"name":"Note","style":"note","type":"aside","content":[{"type":"paragraph","inlineContent":[{"text":"","type":"text"},{"code":"focusOnLocation","type":"codeVoice"},{"text":" and ","type":"text"},{"code":"focusOnFirstLocation","type":"codeVoice"},{"text":" - are deprecated, map will manage it automatically.","type":"text"}]}]},{"text":"Location provider","level":3,"type":"heading","anchor":"Location-provider"},{"items":[{"content":[{"inlineContent":[{"text":"Version 4:","type":"text"}],"type":"paragraph"}]}],"type":"unorderedList"},{"code":["let settings = Settings(locationProvider: YourProvider())","fplanUiView.load(\"https:\/\/demo.expofp.com\", settings: settings)"],"type":"codeListing","syntax":"swift"},{"items":[{"content":[{"inlineContent":[{"text":"Version 5:","type":"text"}],"type":"paragraph"}]}],"type":"unorderedList"},{"code":["let presenter = ExpoFpPlan.createPlanPresenter(","    with: .expoKey(\"demo\"),","    locationProvider: YourProvider()",")"],"type":"codeListing","syntax":"swift"},{"text":"Global location provider","level":3,"type":"heading","anchor":"Global-location-provider"},{"items":[{"content":[{"type":"paragraph","inlineContent":[{"type":"text","text":"Version 4:"}]}]}],"type":"unorderedList"},{"code":["GlobalLocationProvider.initialize(YourProvider())","GlobalLocationProvider.start()","let settings = Settings(useGlobalLocationProvider: true)","","fplanUiView.load(\"https:\/\/demo.expofp.com\", settings: settings)"],"type":"codeListing","syntax":"swift"},{"items":[{"content":[{"inlineContent":[{"type":"text","text":"Version 5:"}],"type":"paragraph"}]}],"type":"unorderedList"},{"code":["ExpoFpPlan.globalLocationProvider.sharedProvider = YourProvider()","","let presenter = ExpoFpPlan.createPlanPresenter(","    with: .expoKey(\"demo\"),","    locationProvider: ExpoFpPlan.globalLocationProvider",")"],"type":"codeListing","syntax":"swift"},{"text":"Plan status","level":3,"type":"heading","anchor":"Plan-status"},{"items":[{"content":[{"type":"paragraph","inlineContent":[{"type":"text","text":"Version 4:"}]}]}],"type":"unorderedList"},{"code":["fplanUiView.setOnFpReadyCallback {","    print(\"[OnFpReady]\")      ","}","","fplanUiView.setOnFpErrorCallback { errorCode, description in","    print(\"[OnFpError] errorCode=\\(errorCode); description=\\(description)\")      ","}"],"type":"codeListing","syntax":"swift"},{"items":[{"content":[{"type":"paragraph","inlineContent":[{"text":"Version 5:","type":"text"}]}]}],"type":"unorderedList"},{"code":["presenter.planStatusPublisher.sink { status in","    switch status {","    case loading(let percentage): print(\"Loading \\(percentage.description)%\")","    case initialization: \/\/ plan is loaded and unfolding","    case error(let cause): print(cause)","    case ready: \/\/ plan is ready to interact","    }","}"],"type":"codeListing","syntax":"swift"},{"text":"Download plan","level":2,"type":"heading","anchor":"Download-plan"},{"inlineContent":[{"code":"ExpoFpOfflinePlanInfoLoader","type":"codeVoice"},{"text":" singleton changed to ","type":"text"},{"code":"ExpoFpPlan.downloader","type":"codeVoice"},{"text":".","type":"text"}],"type":"paragraph"},{"name":"Note","style":"note","type":"aside","content":[{"type":"paragraph","inlineContent":[{"code":"fplanUiView.getFilePathFromCache()","type":"codeVoice"},{"text":" and ","type":"text"},{"code":"fplanUiView.openFileFromCache","type":"codeVoice"},{"text":" - are deprecated. How to download plans or open ","type":"text"},{"inlineContent":[{"type":"text","text":"zip"}],"type":"strong"},{"text":" from bundle look in ","type":"text"},{"isActive":true,"identifier":"doc:\/\/com.expofp.sdk\/documentation\/ExpoFP\/Download-Plan","type":"reference"},{"text":" documentation.","type":"text"}]}]},{"inlineContent":[{"type":"text","text":"Open saved plan:"}],"type":"paragraph"},{"items":[{"content":[{"inlineContent":[{"type":"text","text":"Version 4:"}],"type":"paragraph"}]}],"type":"unorderedList"},{"code":["let plan = UIFplanView()","plan.openFile(with: downloadedPlanInfo)"],"type":"codeListing","syntax":"swift"},{"items":[{"content":[{"inlineContent":[{"text":"Version 5:","type":"text"}],"type":"paragraph"}]}],"type":"unorderedList"},{"code":["let presenter = ExpoFpPlan.createPlanPresenter(with: .downloadedPlanInfo(downloadedPlanInfo))","","\/\/ for UIKit","let viewController = presenter.getViewController()","","\/\/ for SwiftUI","let view = presenter.getView()"],"type":"codeListing","syntax":"swift"},{"text":"Preload plan","level":2,"type":"heading","anchor":"Preload-plan"},{"items":[{"content":[{"type":"paragraph","inlineContent":[{"text":"Version 4:","type":"text"}]}]}],"type":"unorderedList"},{"inlineContent":[{"type":"text","text":"Available only one preloaded plan for the whole app"}],"type":"paragraph"},{"inlineContent":[{"type":"text","text":"SwiftUI:"}],"type":"paragraph"},{"code":["SharedFplanView.preload(\"https:\/\/demo.expofp.com?noOverlay=true\")"],"type":"codeListing","syntax":"swift"},{"inlineContent":[{"text":"UIKit:","type":"text"}],"type":"paragraph"},{"code":["SharedUIFplanView.preload(\"https:\/\/demo.expofp.com?noOverlay=true\")"],"type":"codeListing","syntax":"swift"},{"items":[{"content":[{"inlineContent":[{"type":"text","text":"Version 5:"}],"type":"paragraph"}]}],"type":"unorderedList"},{"inlineContent":[{"text":"You can preload plans with ","type":"text"},{"type":"codeVoice","code":"ExpoKey"},{"text":" from the internet and with ","type":"text"},{"identifier":"doc:\/\/com.expofp.sdk\/documentation\/ExpoFP\/ExpoFpDownloadedPlanInfo","type":"reference","isActive":true},{"text":" from file storage. The number of preloaded plans is unlimited.","type":"text"}],"type":"paragraph"},{"code":["let preloadedPlanInfo = ExpoFpPlan.preloader.preloadPlan(","    with: .expoKey(\"demo\"),","    additionalParams: [ExpoFpPlanParameter.noOverlay(true)]",")","","let presenter = ExpoFpPlan.preloader.getPreloadedPlanPresenter(with: preloadedPlanInfo)","","\/\/ for UIKit","let viewController = presenter.getViewController()","","\/\/ for SwiftUI","let view = presenter.getView()"],"type":"codeListing","syntax":"swift"},{"text":"Commands","level":2,"type":"heading","anchor":"Commands"},{"inlineContent":[{"type":"text","text":"Most of the commands listed in "},{"type":"reference","isActive":true,"identifier":"doc:\/\/com.expofp.sdk\/documentation\/ExpoFP\/Manage-Plan"},{"type":"text","text":" have the same signature as in version 4."}],"type":"paragraph"},{"inlineContent":[{"text":"Commands with a return value wrap values in ","type":"text"},{"identifier":"doc:\/\/com.expofp.sdk\/documentation\/ExpoFP\/ExpoFpResult","type":"reference","isActive":true},{"text":" to intercept and identify errors.","type":"text"}],"type":"paragraph"},{"name":"Note","style":"note","type":"aside","content":[{"type":"paragraph","inlineContent":[{"type":"text","text":"Now all commands you need to call from "},{"type":"codeVoice","code":"presenter"},{"type":"text","text":" instead of "},{"type":"codeVoice","code":"fplanUiView"},{"type":"text","text":" itself, for example: was "},{"type":"codeVoice","code":"fplanUiView.zoomIn()"},{"type":"text","text":" become "},{"type":"codeVoice","code":"presenter.zoomIn()"},{"type":"text","text":"."}]}]},{"text":"Deprecated:","level":3,"type":"heading","anchor":"Deprecated"},{"items":[{"content":[{"type":"paragraph","inlineContent":[{"type":"codeVoice","code":"load(\"https:\/\/demo.expofp.com\")"},{"text":" – use ``ExpoFpPlan\/createPlanPresenter(with:additionalParams:locationProvider:messageListener:isDebugModeEnabled:)","type":"text"}]}]},{"content":[{"inlineContent":[{"type":"codeVoice","code":"clear()"},{"type":"text","text":" - now it’s automatic"}],"type":"paragraph"}]},{"content":[{"type":"paragraph","inlineContent":[{"type":"codeVoice","code":"destroy()"},{"type":"text","text":" - now it’s automatic"}]}]},{"content":[{"inlineContent":[{"code":"selectExhibitor([\"RPMXPO\", \"RPMXP1\"])","type":"codeVoice"},{"text":" - use ","type":"text"},{"identifier":"doc:\/\/com.expofp.sdk\/documentation\/ExpoFP\/IExpoFpPlanPresenter\/selectExhibitor(nameOrExternalId:)","isActive":true,"type":"reference"}],"type":"paragraph"}]},{"content":[{"type":"paragraph","inlineContent":[{"inlineContent":[{"type":"text","text":"all methods"}],"type":"strong"},{"text":" ","type":"text"},{"code":"selectRoute(from:)","type":"codeVoice"},{"text":" - use ","type":"text"},{"isActive":true,"type":"reference","identifier":"doc:\/\/com.expofp.sdk\/documentation\/ExpoFP\/IExpoFpPlanPresenter\/selectRoute(waypoints:)"}]}]}],"type":"unorderedList"},{"text":"Signature changed:","level":3,"type":"heading","anchor":"Signature-changed"},{"items":[{"content":[{"inlineContent":[{"code":"setVisibility(_:)","type":"codeVoice"},{"text":" - now ","type":"text"},{"identifier":"doc:\/\/com.expofp.sdk\/documentation\/ExpoFP\/IExpoFpPlanPresenter\/setElementsVisibility(_:)","type":"reference","isActive":true}],"type":"paragraph"}]},{"content":[{"inlineContent":[{"code":"setCurrentPosition(_:)","type":"codeVoice"},{"text":" - now ","type":"text"},{"identifier":"doc:\/\/com.expofp.sdk\/documentation\/ExpoFP\/IExpoFpPlanPresenter\/selectCurrentPosition(_:focus:)","isActive":true,"type":"reference"}],"type":"paragraph"}]},{"content":[{"inlineContent":[{"type":"codeVoice","code":"getVisibility()"},{"type":"text","text":" - now "},{"type":"reference","isActive":true,"identifier":"doc:\/\/com.expofp.sdk\/documentation\/ExpoFP\/IExpoFpPlanPresenter\/getElementsVisibility()"}],"type":"paragraph"}]}],"type":"unorderedList"},{"text":"Events","level":2,"type":"heading","anchor":"Events"},{"name":"Note","style":"note","type":"aside","content":[{"type":"paragraph","inlineContent":[{"type":"text","text":""},{"type":"codeVoice","code":"fplanUiView.setOnFestDirectionsClick"},{"type":"text","text":" and "},{"type":"codeVoice","code":"fplanUiView.setOnFestMoreDetailsClickCallback"},{"type":"text","text":" - are deprecated."}]}]},{"inlineContent":[{"type":"text","text":"Instead of setting callbacks to a view manually you need to create you own class and confirm it to "},{"type":"reference","isActive":true,"identifier":"doc:\/\/com.expofp.sdk\/documentation\/ExpoFP\/IExpoFpPlanMessageListener"},{"type":"text","text":". Then set your listener to "},{"type":"codeVoice","code":"presenter"},{"type":"text","text":" as shown in "},{"type":"reference","isActive":true,"identifier":"doc:\/\/com.expofp.sdk\/documentation\/ExpoFP\/Listen-Plan-events"},{"type":"text","text":"."}],"type":"paragraph"},{"items":[{"content":[{"type":"paragraph","inlineContent":[{"type":"codeVoice","code":"fplanUiView.setOnBoothClickCallback"},{"type":"text","text":" - now "},{"isActive":true,"type":"reference","identifier":"doc:\/\/com.expofp.sdk\/documentation\/ExpoFP\/IExpoFpPlanMessageListener\/boothDidClick(_:from:)"}]}]},{"content":[{"type":"paragraph","inlineContent":[{"type":"codeVoice","code":"fplanUiView.setOnBuildDirectionCallback"},{"type":"text","text":" - now "},{"type":"reference","identifier":"doc:\/\/com.expofp.sdk\/documentation\/ExpoFP\/IExpoFpPlanMessageListener\/directionDidBuild(_:from:)","isActive":true}]}]},{"content":[{"type":"paragraph","inlineContent":[{"code":"fplanUiView.setOnDetailsClickCallback","type":"codeVoice"},{"text":" - now ","type":"text"},{"isActive":true,"type":"reference","identifier":"doc:\/\/com.expofp.sdk\/documentation\/ExpoFP\/IExpoFpPlanMessageListener\/detailsDidClick(_:from:)"}]}]},{"content":[{"type":"paragraph","inlineContent":[{"code":"fplanUiView.setOnExhibitorCustomButtonClickCallback","type":"codeVoice"},{"text":" - now ","type":"text"},{"identifier":"doc:\/\/com.expofp.sdk\/documentation\/ExpoFP\/IExpoFpPlanMessageListener\/exhibitorCustomButtonDidClick(_:from:)","type":"reference","isActive":true}]}]},{"content":[{"inlineContent":[{"type":"codeVoice","code":"fplanUiView.setOnBookmarkClickCallback"},{"type":"text","text":" - now "},{"isActive":true,"identifier":"doc:\/\/com.expofp.sdk\/documentation\/ExpoFP\/IExpoFpPlanMessageListener\/bookmarkDidClick(_:from:)","type":"reference"}],"type":"paragraph"}]},{"content":[{"type":"paragraph","inlineContent":[{"code":"fplanUiView.setOnCategoryClickCallback","type":"codeVoice"},{"type":"text","text":" - now "},{"isActive":true,"type":"reference","identifier":"doc:\/\/com.expofp.sdk\/documentation\/ExpoFP\/IExpoFpPlanMessageListener\/categoryDidClick(_:from:)"}]}]},{"content":[{"inlineContent":[{"type":"codeVoice","code":"fplanUiView.setOnCurrentPositionChangedCallback"},{"text":" - now ","type":"text"},{"type":"reference","isActive":true,"identifier":"doc:\/\/com.expofp.sdk\/documentation\/ExpoFP\/IExpoFpPlanMessageListener\/currentPositionDidChange(_:from:)"}],"type":"paragraph"}]}],"type":"unorderedList"}],"kind":"content"}],"kind":"article","sections":[],"schemaVersion":{"major":0,"minor":3,"patch":0},"identifier":{"url":"doc:\/\/com.expofp.sdk\/documentation\/ExpoFP\/Migration-guide-from-v4-to-v5","interfaceLanguage":"swift"},"metadata":{"roleHeading":"Article","role":"article","title":"Migration guide from v4 to v5","modules":[{"name":"ExpoFP"}]},"hierarchy":{"paths":[["doc:\/\/com.expofp.sdk\/documentation\/ExpoFP"]]},"abstract":[{"text":"How to easily migrate SDK from version 4 to version 5 and start using new features (approx 5 hours)","type":"text"}],"variants":[{"traits":[{"interfaceLanguage":"swift"}],"paths":["\/documentation\/expofp\/migration-guide-from-v4-to-v5"]}],"references":{"doc://com.expofp.sdk/documentation/ExpoFP/IExpoFpPlanMessageListener/directionDidBuild(_:from:)":{"fragments":[{"text":"func","kind":"keyword"},{"text":" ","kind":"text"},{"text":"directionDidBuild","kind":"identifier"},{"text":"(","kind":"text"},{"preciseIdentifier":"s:6ExpoFP0A8FpResulta","text":"ExpoFpResult","kind":"typeIdentifier"},{"text":"<","kind":"text"},{"preciseIdentifier":"s:6ExpoFP0A11FpDirectionV","text":"ExpoFpDirection","kind":"typeIdentifier"},{"text":"?>, ","kind":"text"},{"text":"from","kind":"externalParam"},{"text":": ","kind":"text"},{"preciseIdentifier":"s:6ExpoFP0A10FpLinkTypeO","text":"ExpoFpLinkType","kind":"typeIdentifier"},{"text":")","kind":"text"}],"type":"topic","identifier":"doc:\/\/com.expofp.sdk\/documentation\/ExpoFP\/IExpoFpPlanMessageListener\/directionDidBuild(_:from:)","url":"\/documentation\/expofp\/iexpofpplanmessagelistener\/directiondidbuild(_:from:)","kind":"symbol","title":"directionDidBuild(_:from:)","abstract":[{"type":"text","text":"Notifies the listener that the Direction has been built or reset."}],"role":"symbol","required":true},"doc://com.expofp.sdk/documentation/ExpoFP/ExpoFpResult":{"identifier":"doc:\/\/com.expofp.sdk\/documentation\/ExpoFP\/ExpoFpResult","fragments":[{"text":"typealias","kind":"keyword"},{"text":" ","kind":"text"},{"text":"ExpoFpResult","kind":"identifier"}],"kind":"symbol","navigatorTitle":[{"text":"ExpoFpResult","kind":"identifier"}],"type":"topic","title":"ExpoFpResult","abstract":[{"type":"text","text":"A value that represents either a success or a failure after command execution."}],"url":"\/documentation\/expofp\/expofpresult","role":"symbol"},"doc://com.expofp.sdk/documentation/ExpoFP/IExpoFpPlanMessageListener/boothDidClick(_:from:)":{"required":true,"title":"boothDidClick(_:from:)","identifier":"doc:\/\/com.expofp.sdk\/documentation\/ExpoFP\/IExpoFpPlanMessageListener\/boothDidClick(_:from:)","url":"\/documentation\/expofp\/iexpofpplanmessagelistener\/boothdidclick(_:from:)","role":"symbol","fragments":[{"text":"func","kind":"keyword"},{"text":" ","kind":"text"},{"text":"boothDidClick","kind":"identifier"},{"text":"(","kind":"text"},{"preciseIdentifier":"s:6ExpoFP0A8FpResulta","text":"ExpoFpResult","kind":"typeIdentifier"},{"text":"<","kind":"text"},{"preciseIdentifier":"s:6ExpoFP0A17FpBoothClickEventV","text":"ExpoFpBoothClickEvent","kind":"typeIdentifier"},{"text":">, ","kind":"text"},{"text":"from","kind":"externalParam"},{"text":": ","kind":"text"},{"preciseIdentifier":"s:6ExpoFP0A10FpLinkTypeO","text":"ExpoFpLinkType","kind":"typeIdentifier"},{"text":")","kind":"text"}],"abstract":[{"text":"Notifies the listener that the Booth has been pressed.","type":"text"}],"type":"topic","kind":"symbol"},"doc://com.expofp.sdk/documentation/ExpoFP/IExpoFpPlanPresenter/selectExhibitor(nameOrExternalId:)":{"kind":"symbol","identifier":"doc:\/\/com.expofp.sdk\/documentation\/ExpoFP\/IExpoFpPlanPresenter\/selectExhibitor(nameOrExternalId:)","abstract":[{"type":"text","text":"Select the specified exibitors."}],"title":"selectExhibitor(nameOrExternalId:)","type":"topic","role":"symbol","url":"\/documentation\/expofp\/iexpofpplanpresenter\/selectexhibitor(nameorexternalid:)","fragments":[{"text":"func","kind":"keyword"},{"text":" ","kind":"text"},{"text":"selectExhibitor","kind":"identifier"},{"text":"(","kind":"text"},{"text":"nameOrExternalId","kind":"externalParam"},{"text":": ","kind":"text"},{"preciseIdentifier":"s:SS","text":"String","kind":"typeIdentifier"},{"text":")","kind":"text"}]},"doc://com.expofp.sdk/documentation/ExpoFP/IExpoFpPlanMessageListener/detailsDidClick(_:from:)":{"required":true,"role":"symbol","abstract":[{"type":"text","text":"Notifies the listener that the Details has been selected or deselected."}],"title":"detailsDidClick(_:from:)","kind":"symbol","identifier":"doc:\/\/com.expofp.sdk\/documentation\/ExpoFP\/IExpoFpPlanMessageListener\/detailsDidClick(_:from:)","url":"\/documentation\/expofp\/iexpofpplanmessagelistener\/detailsdidclick(_:from:)","type":"topic","fragments":[{"text":"func","kind":"keyword"},{"text":" ","kind":"text"},{"text":"detailsDidClick","kind":"identifier"},{"text":"(","kind":"text"},{"text":"ExpoFpResult","kind":"typeIdentifier","preciseIdentifier":"s:6ExpoFP0A8FpResulta"},{"text":"<","kind":"text"},{"text":"ExpoFpDetails","kind":"typeIdentifier","preciseIdentifier":"s:6ExpoFP0A9FpDetailsV"},{"text":"?>, ","kind":"text"},{"text":"from","kind":"externalParam"},{"text":": ","kind":"text"},{"text":"ExpoFpLinkType","kind":"typeIdentifier","preciseIdentifier":"s:6ExpoFP0A10FpLinkTypeO"},{"text":")","kind":"text"}]},"doc://com.expofp.sdk/documentation/ExpoFP/Manage-Plan":{"abstract":[{"type":"text","text":"Apply commands and request information from a plan via "},{"type":"codeVoice","code":"presenter"},{"type":"text","text":"."}],"title":"Manage Plan","kind":"article","role":"article","url":"\/documentation\/expofp\/manage-plan","identifier":"doc:\/\/com.expofp.sdk\/documentation\/ExpoFP\/Manage-Plan","type":"topic"},"doc://com.expofp.sdk/documentation/ExpoFP/IExpoFpPlanMessageListener":{"title":"IExpoFpPlanMessageListener","kind":"symbol","fragments":[{"text":"protocol","kind":"keyword"},{"text":" ","kind":"text"},{"text":"IExpoFpPlanMessageListener","kind":"identifier"}],"type":"topic","role":"symbol","abstract":[{"text":"An interface for receiving messages from Plan.","type":"text"}],"url":"\/documentation\/expofp\/iexpofpplanmessagelistener","identifier":"doc:\/\/com.expofp.sdk\/documentation\/ExpoFP\/IExpoFpPlanMessageListener","navigatorTitle":[{"text":"IExpoFpPlanMessageListener","kind":"identifier"}]},"doc://com.expofp.sdk/documentation/ExpoFP/Listen-Plan-events":{"title":"Listen Plan events","abstract":[{"type":"text","text":"Listen and respond to user interactions with the plan."}],"identifier":"doc:\/\/com.expofp.sdk\/documentation\/ExpoFP\/Listen-Plan-events","url":"\/documentation\/expofp\/listen-plan-events","kind":"article","type":"topic","role":"article"},"doc://com.expofp.sdk/documentation/ExpoFP/IExpoFpPlanPresenter/getElementsVisibility()":{"kind":"symbol","fragments":[{"text":"func","kind":"keyword"},{"text":" ","kind":"text"},{"text":"getElementsVisibility","kind":"identifier"},{"text":"() ","kind":"text"},{"text":"async","kind":"keyword"},{"text":" -> ","kind":"text"},{"text":"ExpoFpResult","kind":"typeIdentifier","preciseIdentifier":"s:6ExpoFP0A8FpResulta"},{"text":"<","kind":"text"},{"text":"ExpoFpElementsVisibility","kind":"typeIdentifier","preciseIdentifier":"s:6ExpoFP0A20FpElementsVisibilityV"},{"text":">","kind":"text"}],"type":"topic","title":"getElementsVisibility()","identifier":"doc:\/\/com.expofp.sdk\/documentation\/ExpoFP\/IExpoFpPlanPresenter\/getElementsVisibility()","role":"symbol","abstract":[{"type":"text","text":"Request information about elements visibility in a plan."}],"url":"\/documentation\/expofp\/iexpofpplanpresenter\/getelementsvisibility()"},"doc://com.expofp.sdk/documentation/ExpoFP/IExpoFpPlanPresenter/selectCurrentPosition(_:focus:)":{"abstract":[{"type":"text","text":"Select the specified position and focus on it."}],"role":"symbol","fragments":[{"kind":"keyword","text":"func"},{"kind":"text","text":" "},{"kind":"identifier","text":"selectCurrentPosition"},{"kind":"text","text":"("},{"preciseIdentifier":"s:6ExpoFP0A10FpPositionV","kind":"typeIdentifier","text":"ExpoFpPosition"},{"kind":"text","text":"?, "},{"kind":"externalParam","text":"focus"},{"kind":"text","text":": "},{"kind":"typeIdentifier","text":"Bool","preciseIdentifier":"s:Sb"},{"kind":"text","text":")"}],"kind":"symbol","url":"\/documentation\/expofp\/iexpofpplanpresenter\/selectcurrentposition(_:focus:)","type":"topic","title":"selectCurrentPosition(_:focus:)","identifier":"doc:\/\/com.expofp.sdk\/documentation\/ExpoFP\/IExpoFpPlanPresenter\/selectCurrentPosition(_:focus:)"},"doc://com.expofp.sdk/documentation/ExpoFP/IExpoFpPlanMessageListener/currentPositionDidChange(_:from:)":{"required":true,"title":"currentPositionDidChange(_:from:)","identifier":"doc:\/\/com.expofp.sdk\/documentation\/ExpoFP\/IExpoFpPlanMessageListener\/currentPositionDidChange(_:from:)","url":"\/documentation\/expofp\/iexpofpplanmessagelistener\/currentpositiondidchange(_:from:)","role":"symbol","fragments":[{"text":"func","kind":"keyword"},{"text":" ","kind":"text"},{"text":"currentPositionDidChange","kind":"identifier"},{"text":"(","kind":"text"},{"preciseIdentifier":"s:6ExpoFP0A8FpResulta","text":"ExpoFpResult","kind":"typeIdentifier"},{"text":"<","kind":"text"},{"preciseIdentifier":"s:6ExpoFP0A10FpPositionV","text":"ExpoFpPosition","kind":"typeIdentifier"},{"text":">, ","kind":"text"},{"text":"from","kind":"externalParam"},{"text":": ","kind":"text"},{"preciseIdentifier":"s:6ExpoFP0A10FpLinkTypeO","text":"ExpoFpLinkType","kind":"typeIdentifier"},{"text":")","kind":"text"}],"abstract":[{"text":"Notifies the listener that the Current Position has been changed.","type":"text"}],"type":"topic","kind":"symbol"},"doc://com.expofp.sdk/documentation/ExpoFP/ExpoFpDownloadedPlanInfo":{"identifier":"doc:\/\/com.expofp.sdk\/documentation\/ExpoFP\/ExpoFpDownloadedPlanInfo","role":"symbol","fragments":[{"kind":"keyword","text":"struct"},{"kind":"text","text":" "},{"kind":"identifier","text":"ExpoFpDownloadedPlanInfo"}],"abstract":[{"text":"Information about the saved plan in the cache directory.","type":"text"}],"title":"ExpoFpDownloadedPlanInfo","type":"topic","url":"\/documentation\/expofp\/expofpdownloadedplaninfo","kind":"symbol","navigatorTitle":[{"kind":"identifier","text":"ExpoFpDownloadedPlanInfo"}]},"doc://com.expofp.sdk/documentation/ExpoFP":{"role":"collection","type":"topic","identifier":"doc:\/\/com.expofp.sdk\/documentation\/ExpoFP","url":"\/documentation\/expofp","abstract":[{"type":"text","text":"A binary package (XCFramework) to show and manage floor plans."}],"title":"ExpoFP","kind":"symbol"},"doc://com.expofp.sdk/documentation/ExpoFP/IExpoFpPlanMessageListener/categoryDidClick(_:from:)":{"url":"\/documentation\/expofp\/iexpofpplanmessagelistener\/categorydidclick(_:from:)","identifier":"doc:\/\/com.expofp.sdk\/documentation\/ExpoFP\/IExpoFpPlanMessageListener\/categoryDidClick(_:from:)","type":"topic","required":true,"title":"categoryDidClick(_:from:)","kind":"symbol","abstract":[{"type":"text","text":"Notifies the listener that the Category has been selected."}],"role":"symbol","fragments":[{"text":"func","kind":"keyword"},{"text":" ","kind":"text"},{"text":"categoryDidClick","kind":"identifier"},{"text":"(","kind":"text"},{"text":"ExpoFpResult","kind":"typeIdentifier","preciseIdentifier":"s:6ExpoFP0A8FpResulta"},{"text":"<","kind":"text"},{"text":"ExpoFpCategory","kind":"typeIdentifier","preciseIdentifier":"s:6ExpoFP0A10FpCategoryV"},{"text":">, ","kind":"text"},{"text":"from","kind":"externalParam"},{"text":": ","kind":"text"},{"text":"ExpoFpLinkType","kind":"typeIdentifier","preciseIdentifier":"s:6ExpoFP0A10FpLinkTypeO"},{"kind":"text","text":")"}]},"doc://com.expofp.sdk/documentation/ExpoFP/IExpoFpPlanPresenter/selectRoute(waypoints:)":{"abstract":[{"type":"text","text":"Build the specified route."}],"url":"\/documentation\/expofp\/iexpofpplanpresenter\/selectroute(waypoints:)","fragments":[{"text":"func","kind":"keyword"},{"text":" ","kind":"text"},{"text":"selectRoute","kind":"identifier"},{"text":"(","kind":"text"},{"text":"waypoints","kind":"externalParam"},{"text":": [","kind":"text"},{"preciseIdentifier":"s:6ExpoFP0A15FpRouteWaypointO","text":"ExpoFpRouteWaypoint","kind":"typeIdentifier"},{"text":"])","kind":"text"}],"title":"selectRoute(waypoints:)","kind":"symbol","role":"symbol","identifier":"doc:\/\/com.expofp.sdk\/documentation\/ExpoFP\/IExpoFpPlanPresenter\/selectRoute(waypoints:)","type":"topic"},"doc://com.expofp.sdk/documentation/ExpoFP/IExpoFpPlanMessageListener/exhibitorCustomButtonDidClick(_:from:)":{"url":"\/documentation\/expofp\/iexpofpplanmessagelistener\/exhibitorcustombuttondidclick(_:from:)","identifier":"doc:\/\/com.expofp.sdk\/documentation\/ExpoFP\/IExpoFpPlanMessageListener\/exhibitorCustomButtonDidClick(_:from:)","type":"topic","required":true,"title":"exhibitorCustomButtonDidClick(_:from:)","kind":"symbol","abstract":[{"type":"text","text":"Notifies the listener that the Custom Button has been pressed."}],"role":"symbol","fragments":[{"text":"func","kind":"keyword"},{"text":" ","kind":"text"},{"text":"exhibitorCustomButtonDidClick","kind":"identifier"},{"text":"(","kind":"text"},{"text":"ExpoFpResult","kind":"typeIdentifier","preciseIdentifier":"s:6ExpoFP0A8FpResulta"},{"text":"<","kind":"text"},{"text":"ExpoFpCustomButtonEvent","kind":"typeIdentifier","preciseIdentifier":"s:6ExpoFP0A19FpCustomButtonEventV"},{"text":">, ","kind":"text"},{"text":"from","kind":"externalParam"},{"text":": ","kind":"text"},{"text":"ExpoFpLinkType","kind":"typeIdentifier","preciseIdentifier":"s:6ExpoFP0A10FpLinkTypeO"},{"text":")","kind":"text"}]},"doc://com.expofp.sdk/documentation/ExpoFP/IExpoFpPlanPresenter/setElementsVisibility(_:)":{"title":"setElementsVisibility(_:)","url":"\/documentation\/expofp\/iexpofpplanpresenter\/setelementsvisibility(_:)","identifier":"doc:\/\/com.expofp.sdk\/documentation\/ExpoFP\/IExpoFpPlanPresenter\/setElementsVisibility(_:)","kind":"symbol","fragments":[{"kind":"keyword","text":"func"},{"kind":"text","text":" "},{"kind":"identifier","text":"setElementsVisibility"},{"kind":"text","text":"("},{"preciseIdentifier":"s:6ExpoFP0A20FpElementsVisibilityV","kind":"typeIdentifier","text":"ExpoFpElementsVisibility"},{"kind":"text","text":")"}],"abstract":[{"type":"text","text":"Enable or disable elements visibility in a plan."}],"type":"topic","role":"symbol"},"doc://com.expofp.sdk/documentation/ExpoFP/Download-Plan":{"title":"Download Plan","url":"\/documentation\/expofp\/download-plan","kind":"article","role":"article","identifier":"doc:\/\/com.expofp.sdk\/documentation\/ExpoFP\/Download-Plan","type":"topic","abstract":[{"text":"Save plans in mobile file storage and use them without the internet.","type":"text"}]},"doc://com.expofp.sdk/documentation/ExpoFP/IExpoFpPlanMessageListener/bookmarkDidClick(_:from:)":{"role":"symbol","kind":"symbol","fragments":[{"kind":"keyword","text":"func"},{"kind":"text","text":" "},{"kind":"identifier","text":"bookmarkDidClick"},{"kind":"text","text":"("},{"kind":"typeIdentifier","preciseIdentifier":"s:6ExpoFP0A8FpResulta","text":"ExpoFpResult"},{"kind":"text","text":"<"},{"kind":"typeIdentifier","preciseIdentifier":"s:6ExpoFP0A10FpBookmarkV","text":"ExpoFpBookmark"},{"kind":"text","text":">, "},{"kind":"externalParam","text":"from"},{"kind":"text","text":": "},{"kind":"typeIdentifier","preciseIdentifier":"s:6ExpoFP0A10FpLinkTypeO","text":"ExpoFpLinkType"},{"kind":"text","text":")"}],"title":"bookmarkDidClick(_:from:)","required":true,"url":"\/documentation\/expofp\/iexpofpplanmessagelistener\/bookmarkdidclick(_:from:)","abstract":[{"type":"text","text":"Notifies the listener that the Bookmark button has been pressed."}],"identifier":"doc:\/\/com.expofp.sdk\/documentation\/ExpoFP\/IExpoFpPlanMessageListener\/bookmarkDidClick(_:from:)","type":"topic"}}}