{"hierarchy":{"paths":[[]]},"abstract":[{"text":"A binary package (XCFramework) to show and manage floor plans.","type":"text"}],"topicSections":[{"identifiers":["doc:\/\/com.expofp.sdk\/documentation\/ExpoFP\/Load-Plan","doc:\/\/com.expofp.sdk\/documentation\/ExpoFP\/Download-Plan","doc:\/\/com.expofp.sdk\/documentation\/ExpoFP\/Preload-Plan","doc:\/\/com.expofp.sdk\/documentation\/ExpoFP\/Manage-properties-and-settings","doc:\/\/com.expofp.sdk\/documentation\/ExpoFP\/Manage-Plan","doc:\/\/com.expofp.sdk\/documentation\/ExpoFP\/Listen-Plan-events","doc:\/\/com.expofp.sdk\/documentation\/ExpoFP\/Setup-navigation"],"anchor":"Topics"},{"identifiers":["doc:\/\/com.expofp.sdk\/documentation\/ExpoFP\/Migration-guide-from-v4-to-v5"],"anchor":"Articles","generated":true,"title":"Articles"},{"identifiers":["doc:\/\/com.expofp.sdk\/documentation\/ExpoFP\/ExpoFpGlobalLocationProvider","doc:\/\/com.expofp.sdk\/documentation\/ExpoFP\/ExpoFpPreloadedPlanInfo"],"anchor":"Classes","generated":true,"title":"Classes"},{"identifiers":["doc:\/\/com.expofp.sdk\/documentation\/ExpoFP\/ExpoFpLocationProviderDelegate","doc:\/\/com.expofp.sdk\/documentation\/ExpoFP\/IExpoFpLocationProvider","doc:\/\/com.expofp.sdk\/documentation\/ExpoFP\/IExpoFpPlanMessageListener","doc:\/\/com.expofp.sdk\/documentation\/ExpoFP\/IExpoFpPlanPresenter"],"anchor":"Protocols","generated":true,"title":"Protocols"},{"identifiers":["doc:\/\/com.expofp.sdk\/documentation\/ExpoFP\/ExpoFpBookmark","doc:\/\/com.expofp.sdk\/documentation\/ExpoFP\/ExpoFpBooth","doc:\/\/com.expofp.sdk\/documentation\/ExpoFP\/ExpoFpBoothClickEvent","doc:\/\/com.expofp.sdk\/documentation\/ExpoFP\/ExpoFpCategory","doc:\/\/com.expofp.sdk\/documentation\/ExpoFP\/ExpoFpConsoleMessage","doc:\/\/com.expofp.sdk\/documentation\/ExpoFP\/ExpoFpCustomButtonEvent","doc:\/\/com.expofp.sdk\/documentation\/ExpoFP\/ExpoFpDetails","doc:\/\/com.expofp.sdk\/documentation\/ExpoFP\/ExpoFpDirection","doc:\/\/com.expofp.sdk\/documentation\/ExpoFP\/ExpoFpDownloadedPlanInfo","doc:\/\/com.expofp.sdk\/documentation\/ExpoFP\/ExpoFpElementsVisibility","doc:\/\/com.expofp.sdk\/documentation\/ExpoFP\/ExpoFpExhibitor","doc:\/\/com.expofp.sdk\/documentation\/ExpoFP\/ExpoFpLayer","doc:\/\/com.expofp.sdk\/documentation\/ExpoFP\/ExpoFpLine","doc:\/\/com.expofp.sdk\/documentation\/ExpoFP\/ExpoFpPlanDownloader","doc:\/\/com.expofp.sdk\/documentation\/ExpoFP\/ExpoFpPlanPreloader","doc:\/\/com.expofp.sdk\/documentation\/ExpoFP\/ExpoFpPoint","doc:\/\/com.expofp.sdk\/documentation\/ExpoFP\/ExpoFpPosition","doc:\/\/com.expofp.sdk\/documentation\/ExpoFP\/ExpoFpRouteInfo","doc:\/\/com.expofp.sdk\/documentation\/ExpoFP\/ExpoFpSchedule","doc:\/\/com.expofp.sdk\/documentation\/ExpoFP\/ExpoFpSearchModel","doc:\/\/com.expofp.sdk\/documentation\/ExpoFP\/ExpoFpUnknownSearchItem","doc:\/\/com.expofp.sdk\/documentation\/ExpoFP\/ExpoFpVisitedClickEvent","doc:\/\/com.expofp.sdk\/documentation\/ExpoFP\/ExpoFpWindowError"],"anchor":"Structures","generated":true,"title":"Structures"},{"identifiers":["doc:\/\/com.expofp.sdk\/documentation\/ExpoFP\/ExpoFpDownloadedPlanInfoResult","doc:\/\/com.expofp.sdk\/documentation\/ExpoFP\/ExpoFpPlanStatusPublisher","doc:\/\/com.expofp.sdk\/documentation\/ExpoFP\/ExpoFpResult"],"anchor":"Type-Aliases","generated":true,"title":"Type Aliases"},{"identifiers":["doc:\/\/com.expofp.sdk\/documentation\/ExpoFP\/ExpoFpDetailsType","doc:\/\/com.expofp.sdk\/documentation\/ExpoFP\/ExpoFpError","doc:\/\/com.expofp.sdk\/documentation\/ExpoFP\/ExpoFpFloor","doc:\/\/com.expofp.sdk\/documentation\/ExpoFP\/ExpoFpLinkType","doc:\/\/com.expofp.sdk\/documentation\/ExpoFP\/ExpoFpPlan","doc:\/\/com.expofp.sdk\/documentation\/ExpoFP\/ExpoFpPlanStatus","doc:\/\/com.expofp.sdk\/documentation\/ExpoFP\/ExpoFpRouteWaypoint","doc:\/\/com.expofp.sdk\/documentation\/ExpoFP\/ExpoFpSearchItemType"],"anchor":"Enumerations","generated":true,"title":"Enumerations"}],"identifier":{"interfaceLanguage":"swift","url":"doc:\/\/com.expofp.sdk\/documentation\/ExpoFP"},"primaryContentSections":[{"kind":"content","content":[{"type":"heading","anchor":"Whats-new-in-ExpoFP-SDK-version-5","text":"What’s new in ExpoFP SDK version 5","level":2},{"type":"unorderedList","items":[{"content":[{"type":"paragraph","inlineContent":[{"text":"SDK architecture has been completely redesigned, now a ","type":"text"},{"type":"strong","inlineContent":[{"code":"presenter","type":"codeVoice"}]},{"text":" is responsible for managing a plan","type":"text"}]}]},{"content":[{"inlineContent":[{"type":"text","text":"UI layer is passive, reusable and lightweight"}],"type":"paragraph"}]},{"content":[{"type":"paragraph","inlineContent":[{"type":"text","text":"Implemented support for async\/await"}]}]},{"content":[{"inlineContent":[{"text":"You can download an unlimited number of plans for offline use","type":"text"}],"type":"paragraph"}]},{"content":[{"inlineContent":[{"text":"You can preload downloaded plans and plans from the internet for later use, no limits","type":"text"}],"type":"paragraph"}]},{"content":[{"inlineContent":[{"type":"text","text":"Improved stability and loading speed"}],"type":"paragraph"}]},{"content":[{"type":"paragraph","inlineContent":[{"type":"text","text":"Location provider wrappers are now open source"}]}]}]},{"type":"heading","anchor":"Migration-from-previous-version","text":"Migration from previous version","level":2},{"type":"unorderedList","items":[{"content":[{"type":"paragraph","inlineContent":[{"identifier":"doc:\/\/com.expofp.sdk\/documentation\/ExpoFP\/Migration-guide-from-v4-to-v5","isActive":true,"type":"reference"}]}]}]},{"type":"heading","anchor":"Setup","text":"Setup","level":2},{"type":"heading","anchor":"SPM","text":"SPM","level":4},{"type":"codeListing","syntax":"swift","code":["dependencies: [","    .package(url: \"https:\/\/github.com\/expofp\/expofp-sdk-ios\", from: \"5.0.1\"),","]"]},{"type":"paragraph","inlineContent":[{"text":"and add it to your target’s dependencies","type":"text"}]},{"type":"codeListing","syntax":"swift","code":[".target(","    name: \"MyApp\",","    dependencies: [","        .product(name: \"ExpoFP\", package: \"expofp-sdk-ios\"),","    ]","),"]},{"type":"heading","anchor":"CocoaPods","text":"CocoaPods","level":4},{"style":"warning","type":"aside","name":"Warning","content":[{"type":"paragraph","inlineContent":[{"type":"text","text":"CocoaPods "},{"type":"reference","identifier":"https:\/\/blog.cocoapods.org\/CocoaPods-Specs-Repo\/","isActive":true}]}]},{"type":"codeListing","syntax":null,"code":["target 'MyApp' do","    pod 'ExpoFP', '~> 5.0.1'","end"]}]}],"variants":[{"traits":[{"interfaceLanguage":"swift"}],"paths":["\/documentation\/expofp"]}],"sections":[],"kind":"symbol","schemaVersion":{"patch":0,"minor":3,"major":0},"metadata":{"title":"ExpoFP","symbolKind":"module","roleHeading":"Framework","externalID":"ExpoFP","modules":[{"name":"ExpoFP"}],"role":"collection"},"references":{"doc://com.expofp.sdk/documentation/ExpoFP/ExpoFpWindowError":{"role":"symbol","title":"ExpoFpWindowError","kind":"symbol","navigatorTitle":[{"kind":"identifier","text":"ExpoFpWindowError"}],"abstract":[{"type":"text","text":"Information about "},{"type":"codeVoice","code":"window.onerror"},{"type":"text","text":" message"}],"identifier":"doc:\/\/com.expofp.sdk\/documentation\/ExpoFP\/ExpoFpWindowError","url":"\/documentation\/expofp\/expofpwindowerror","type":"topic","fragments":[{"kind":"keyword","text":"struct"},{"kind":"text","text":" "},{"kind":"identifier","text":"ExpoFpWindowError"}]},"doc://com.expofp.sdk/documentation/ExpoFP/ExpoFpVisitedClickEvent":{"title":"ExpoFpVisitedClickEvent","kind":"symbol","fragments":[{"text":"struct","kind":"keyword"},{"text":" ","kind":"text"},{"text":"ExpoFpVisitedClickEvent","kind":"identifier"}],"navigatorTitle":[{"kind":"identifier","text":"ExpoFpVisitedClickEvent"}],"identifier":"doc:\/\/com.expofp.sdk\/documentation\/ExpoFP\/ExpoFpVisitedClickEvent","url":"\/documentation\/expofp\/expofpvisitedclickevent","abstract":[{"type":"text","text":"Visited Booth info"}],"role":"symbol","type":"topic"},"doc://com.expofp.sdk/documentation/ExpoFP/ExpoFpDetailsType":{"title":"ExpoFpDetailsType","fragments":[{"text":"enum","kind":"keyword"},{"kind":"text","text":" "},{"kind":"identifier","text":"ExpoFpDetailsType"}],"abstract":[{"text":"Details type","type":"text"}],"role":"symbol","type":"topic","url":"\/documentation\/expofp\/expofpdetailstype","navigatorTitle":[{"kind":"identifier","text":"ExpoFpDetailsType"}],"kind":"symbol","identifier":"doc:\/\/com.expofp.sdk\/documentation\/ExpoFP\/ExpoFpDetailsType"},"doc://com.expofp.sdk/documentation/ExpoFP/ExpoFpSchedule":{"title":"ExpoFpSchedule","fragments":[{"kind":"keyword","text":"struct"},{"kind":"text","text":" "},{"kind":"identifier","text":"ExpoFpSchedule"}],"identifier":"doc:\/\/com.expofp.sdk\/documentation\/ExpoFP\/ExpoFpSchedule","kind":"symbol","type":"topic","abstract":[{"type":"text","text":"Schedule info about an item"}],"role":"symbol","url":"\/documentation\/expofp\/expofpschedule","navigatorTitle":[{"kind":"identifier","text":"ExpoFpSchedule"}]},"doc://com.expofp.sdk/documentation/ExpoFP/ExpoFpRouteInfo":{"fragments":[{"text":"struct","kind":"keyword"},{"text":" ","kind":"text"},{"text":"ExpoFpRouteInfo","kind":"identifier"}],"navigatorTitle":[{"text":"ExpoFpRouteInfo","kind":"identifier"}],"abstract":[{"type":"text","text":"Information about the optimized route"}],"title":"ExpoFpRouteInfo","role":"symbol","kind":"symbol","type":"topic","url":"\/documentation\/expofp\/expofprouteinfo","identifier":"doc:\/\/com.expofp.sdk\/documentation\/ExpoFP\/ExpoFpRouteInfo"},"doc://com.expofp.sdk/documentation/ExpoFP/ExpoFpSearchItemType":{"kind":"symbol","type":"topic","title":"ExpoFpSearchItemType","abstract":[{"text":"Type of the search item","type":"text"}],"identifier":"doc:\/\/com.expofp.sdk\/documentation\/ExpoFP\/ExpoFpSearchItemType","role":"symbol","navigatorTitle":[{"text":"ExpoFpSearchItemType","kind":"identifier"}],"fragments":[{"text":"enum","kind":"keyword"},{"text":" ","kind":"text"},{"text":"ExpoFpSearchItemType","kind":"identifier"}],"url":"\/documentation\/expofp\/expofpsearchitemtype"},"doc://com.expofp.sdk/documentation/ExpoFP/ExpoFpGlobalLocationProvider":{"kind":"symbol","abstract":[{"type":"text","text":"Singleton wrapper around a location provider."}],"type":"topic","identifier":"doc:\/\/com.expofp.sdk\/documentation\/ExpoFP\/ExpoFpGlobalLocationProvider","url":"\/documentation\/expofp\/expofpgloballocationprovider","title":"ExpoFpGlobalLocationProvider","fragments":[{"text":"class","kind":"keyword"},{"text":" ","kind":"text"},{"text":"ExpoFpGlobalLocationProvider","kind":"identifier"}],"navigatorTitle":[{"text":"ExpoFpGlobalLocationProvider","kind":"identifier"}],"role":"symbol"},"doc://com.expofp.sdk/documentation/ExpoFP/IExpoFpLocationProvider":{"type":"topic","fragments":[{"text":"protocol","kind":"keyword"},{"text":" ","kind":"text"},{"text":"IExpoFpLocationProvider","kind":"identifier"}],"identifier":"doc:\/\/com.expofp.sdk\/documentation\/ExpoFP\/IExpoFpLocationProvider","abstract":[{"type":"text","text":"Protocol for embedding a location provider into a plan."}],"navigatorTitle":[{"text":"IExpoFpLocationProvider","kind":"identifier"}],"kind":"symbol","title":"IExpoFpLocationProvider","role":"symbol","url":"\/documentation\/expofp\/iexpofplocationprovider"},"doc://com.expofp.sdk/documentation/ExpoFP/ExpoFpBookmark":{"identifier":"doc:\/\/com.expofp.sdk\/documentation\/ExpoFP\/ExpoFpBookmark","abstract":[{"text":"Bookmarked Booth info","type":"text"}],"navigatorTitle":[{"text":"ExpoFpBookmark","kind":"identifier"}],"url":"\/documentation\/expofp\/expofpbookmark","role":"symbol","fragments":[{"text":"struct","kind":"keyword"},{"text":" ","kind":"text"},{"text":"ExpoFpBookmark","kind":"identifier"}],"kind":"symbol","type":"topic","title":"ExpoFpBookmark"},"doc://com.expofp.sdk/documentation/ExpoFP/ExpoFpCustomButtonEvent":{"title":"ExpoFpCustomButtonEvent","type":"topic","url":"\/documentation\/expofp\/expofpcustombuttonevent","abstract":[{"type":"text","text":"Custom button click event params"}],"role":"symbol","identifier":"doc:\/\/com.expofp.sdk\/documentation\/ExpoFP\/ExpoFpCustomButtonEvent","navigatorTitle":[{"kind":"identifier","text":"ExpoFpCustomButtonEvent"}],"kind":"symbol","fragments":[{"kind":"keyword","text":"struct"},{"kind":"text","text":" "},{"kind":"identifier","text":"ExpoFpCustomButtonEvent"}]},"doc://com.expofp.sdk/documentation/ExpoFP/ExpoFpFloor":{"kind":"symbol","title":"ExpoFpFloor","type":"topic","identifier":"doc:\/\/com.expofp.sdk\/documentation\/ExpoFP\/ExpoFpFloor","fragments":[{"kind":"keyword","text":"enum"},{"kind":"text","text":" "},{"kind":"identifier","text":"ExpoFpFloor"}],"role":"symbol","navigatorTitle":[{"kind":"identifier","text":"ExpoFpFloor"}],"abstract":[{"type":"text","text":"Floor index or name"}],"url":"\/documentation\/expofp\/expofpfloor"},"doc://com.expofp.sdk/documentation/ExpoFP/ExpoFpLayer":{"kind":"symbol","title":"ExpoFpLayer","url":"\/documentation\/expofp\/expofplayer","navigatorTitle":[{"kind":"identifier","text":"ExpoFpLayer"}],"fragments":[{"text":"struct","kind":"keyword"},{"kind":"text","text":" "},{"kind":"identifier","text":"ExpoFpLayer"}],"type":"topic","identifier":"doc:\/\/com.expofp.sdk\/documentation\/ExpoFP\/ExpoFpLayer","role":"symbol","abstract":[{"text":"Layer info","type":"text"}]},"doc://com.expofp.sdk/documentation/ExpoFP/ExpoFpLocationProviderDelegate":{"role":"symbol","identifier":"doc:\/\/com.expofp.sdk\/documentation\/ExpoFP\/ExpoFpLocationProviderDelegate","abstract":[{"type":"text","text":"Delegate to receive location provider events."}],"kind":"symbol","type":"topic","fragments":[{"kind":"keyword","text":"protocol"},{"kind":"text","text":" "},{"kind":"identifier","text":"ExpoFpLocationProviderDelegate"}],"navigatorTitle":[{"kind":"identifier","text":"ExpoFpLocationProviderDelegate"}],"url":"\/documentation\/expofp\/expofplocationproviderdelegate","title":"ExpoFpLocationProviderDelegate"},"doc://com.expofp.sdk/documentation/ExpoFP/Load-Plan":{"title":"Load and show Plan","abstract":[{"text":"Basic way to show a plan from the internet.","type":"text"}],"role":"article","kind":"article","url":"\/documentation\/expofp\/load-plan","type":"topic","identifier":"doc:\/\/com.expofp.sdk\/documentation\/ExpoFP\/Load-Plan"},"doc://com.expofp.sdk/documentation/ExpoFP":{"abstract":[{"text":"A binary package (XCFramework) to show and manage floor plans.","type":"text"}],"title":"ExpoFP","url":"\/documentation\/expofp","kind":"symbol","role":"collection","type":"topic","identifier":"doc:\/\/com.expofp.sdk\/documentation\/ExpoFP"},"doc://com.expofp.sdk/documentation/ExpoFP/ExpoFpLinkType":{"abstract":[{"text":"Type of the link to load a plan.","type":"text"}],"title":"ExpoFpLinkType","type":"topic","kind":"symbol","role":"symbol","fragments":[{"text":"enum","kind":"keyword"},{"text":" ","kind":"text"},{"text":"ExpoFpLinkType","kind":"identifier"}],"navigatorTitle":[{"text":"ExpoFpLinkType","kind":"identifier"}],"identifier":"doc:\/\/com.expofp.sdk\/documentation\/ExpoFP\/ExpoFpLinkType","url":"\/documentation\/expofp\/expofplinktype"},"doc://com.expofp.sdk/documentation/ExpoFP/ExpoFpPlan":{"abstract":[{"type":"text","text":"An entry point to ExpoFP functionality."}],"url":"\/documentation\/expofp\/expofpplan","role":"symbol","fragments":[{"kind":"keyword","text":"enum"},{"kind":"text","text":" "},{"kind":"identifier","text":"ExpoFpPlan"}],"kind":"symbol","type":"topic","title":"ExpoFpPlan","navigatorTitle":[{"kind":"identifier","text":"ExpoFpPlan"}],"identifier":"doc:\/\/com.expofp.sdk\/documentation\/ExpoFP\/ExpoFpPlan"},"doc://com.expofp.sdk/documentation/ExpoFP/ExpoFpPoint":{"title":"ExpoFpPoint","abstract":[{"type":"text","text":"Point on floor plan"}],"kind":"symbol","navigatorTitle":[{"text":"ExpoFpPoint","kind":"identifier"}],"identifier":"doc:\/\/com.expofp.sdk\/documentation\/ExpoFP\/ExpoFpPoint","url":"\/documentation\/expofp\/expofppoint","fragments":[{"text":"struct","kind":"keyword"},{"text":" ","kind":"text"},{"text":"ExpoFpPoint","kind":"identifier"}],"type":"topic","role":"symbol"},"doc://com.expofp.sdk/documentation/ExpoFP/ExpoFpPlanStatus":{"url":"\/documentation\/expofp\/expofpplanstatus","type":"topic","role":"symbol","identifier":"doc:\/\/com.expofp.sdk\/documentation\/ExpoFP\/ExpoFpPlanStatus","title":"ExpoFpPlanStatus","kind":"symbol","fragments":[{"text":"enum","kind":"keyword"},{"text":" ","kind":"text"},{"text":"ExpoFpPlanStatus","kind":"identifier"}],"abstract":[{"text":"Status of a plan during its life cycle.","type":"text"}],"navigatorTitle":[{"text":"ExpoFpPlanStatus","kind":"identifier"}]},"doc://com.expofp.sdk/documentation/ExpoFP/ExpoFpExhibitor":{"fragments":[{"kind":"keyword","text":"struct"},{"text":" ","kind":"text"},{"text":"ExpoFpExhibitor","kind":"identifier"}],"kind":"symbol","role":"symbol","url":"\/documentation\/expofp\/expofpexhibitor","navigatorTitle":[{"kind":"identifier","text":"ExpoFpExhibitor"}],"abstract":[{"type":"text","text":"Exhibitor info"}],"title":"ExpoFpExhibitor","identifier":"doc:\/\/com.expofp.sdk\/documentation\/ExpoFP\/ExpoFpExhibitor","type":"topic"},"doc://com.expofp.sdk/documentation/ExpoFP/ExpoFpDetails":{"identifier":"doc:\/\/com.expofp.sdk\/documentation\/ExpoFP\/ExpoFpDetails","abstract":[{"type":"text","text":"Information about opened details panel"}],"fragments":[{"text":"struct","kind":"keyword"},{"text":" ","kind":"text"},{"text":"ExpoFpDetails","kind":"identifier"}],"title":"ExpoFpDetails","url":"\/documentation\/expofp\/expofpdetails","navigatorTitle":[{"text":"ExpoFpDetails","kind":"identifier"}],"type":"topic","role":"symbol","kind":"symbol"},"doc://com.expofp.sdk/documentation/ExpoFP/ExpoFpPlanStatusPublisher":{"type":"topic","identifier":"doc:\/\/com.expofp.sdk\/documentation\/ExpoFP\/ExpoFpPlanStatusPublisher","abstract":[{"text":"A publisher that notifies about plan loading statuses and navigation errors.","type":"text"}],"fragments":[{"text":"typealias","kind":"keyword"},{"text":" ","kind":"text"},{"text":"ExpoFpPlanStatusPublisher","kind":"identifier"}],"navigatorTitle":[{"text":"ExpoFpPlanStatusPublisher","kind":"identifier"}],"kind":"symbol","title":"ExpoFpPlanStatusPublisher","url":"\/documentation\/expofp\/expofpplanstatuspublisher","role":"symbol"},"doc://com.expofp.sdk/documentation/ExpoFP/Preload-Plan":{"identifier":"doc:\/\/com.expofp.sdk\/documentation\/ExpoFP\/Preload-Plan","title":"Preload Plan","kind":"article","role":"article","abstract":[{"type":"text","text":"Preload plans in advance and reuse them without the internet during an app lifecycle."}],"type":"topic","url":"\/documentation\/expofp\/preload-plan"},"doc://com.expofp.sdk/documentation/ExpoFP/ExpoFpPreloadedPlanInfo":{"kind":"symbol","fragments":[{"text":"class","kind":"keyword"},{"text":" ","kind":"text"},{"text":"ExpoFpPreloadedPlanInfo","kind":"identifier"}],"role":"symbol","abstract":[{"text":"Information about preloadeded plan.","type":"text"}],"type":"topic","url":"\/documentation\/expofp\/expofppreloadedplaninfo","identifier":"doc:\/\/com.expofp.sdk\/documentation\/ExpoFP\/ExpoFpPreloadedPlanInfo","navigatorTitle":[{"text":"ExpoFpPreloadedPlanInfo","kind":"identifier"}],"title":"ExpoFpPreloadedPlanInfo"},"doc://com.expofp.sdk/documentation/ExpoFP/IExpoFpPlanMessageListener":{"kind":"symbol","abstract":[{"type":"text","text":"An interface for receiving messages from Plan."}],"identifier":"doc:\/\/com.expofp.sdk\/documentation\/ExpoFP\/IExpoFpPlanMessageListener","type":"topic","url":"\/documentation\/expofp\/iexpofpplanmessagelistener","role":"symbol","fragments":[{"text":"protocol","kind":"keyword"},{"text":" ","kind":"text"},{"text":"IExpoFpPlanMessageListener","kind":"identifier"}],"title":"IExpoFpPlanMessageListener","navigatorTitle":[{"text":"IExpoFpPlanMessageListener","kind":"identifier"}]},"doc://com.expofp.sdk/documentation/ExpoFP/ExpoFpBooth":{"title":"ExpoFpBooth","identifier":"doc:\/\/com.expofp.sdk\/documentation\/ExpoFP\/ExpoFpBooth","url":"\/documentation\/expofp\/expofpbooth","role":"symbol","kind":"symbol","abstract":[{"text":"Booth info","type":"text"}],"fragments":[{"text":"struct","kind":"keyword"},{"text":" ","kind":"text"},{"text":"ExpoFpBooth","kind":"identifier"}],"type":"topic","navigatorTitle":[{"kind":"identifier","text":"ExpoFpBooth"}]},"doc://com.expofp.sdk/documentation/ExpoFP/ExpoFpPosition":{"title":"ExpoFpPosition","navigatorTitle":[{"text":"ExpoFpPosition","kind":"identifier"}],"url":"\/documentation\/expofp\/expofpposition","kind":"symbol","type":"topic","identifier":"doc:\/\/com.expofp.sdk\/documentation\/ExpoFP\/ExpoFpPosition","fragments":[{"text":"struct","kind":"keyword"},{"text":" ","kind":"text"},{"text":"ExpoFpPosition","kind":"identifier"}],"role":"symbol","abstract":[{"type":"text","text":"Position info"}]},"doc://com.expofp.sdk/documentation/ExpoFP/ExpoFpDownloadedPlanInfoResult":{"identifier":"doc:\/\/com.expofp.sdk\/documentation\/ExpoFP\/ExpoFpDownloadedPlanInfoResult","kind":"symbol","role":"symbol","abstract":[],"type":"topic","fragments":[{"text":"typealias","kind":"keyword"},{"text":" ","kind":"text"},{"text":"ExpoFpDownloadedPlanInfoResult","kind":"identifier"}],"title":"ExpoFpDownloadedPlanInfoResult","url":"\/documentation\/expofp\/expofpdownloadedplaninforesult","navigatorTitle":[{"text":"ExpoFpDownloadedPlanInfoResult","kind":"identifier"}]},"doc://com.expofp.sdk/documentation/ExpoFP/Download-Plan":{"kind":"article","identifier":"doc:\/\/com.expofp.sdk\/documentation\/ExpoFP\/Download-Plan","role":"article","title":"Download Plan","type":"topic","url":"\/documentation\/expofp\/download-plan","abstract":[{"text":"Save plans in mobile file storage and use them without the internet.","type":"text"}]},"doc://com.expofp.sdk/documentation/ExpoFP/ExpoFpSearchModel":{"role":"symbol","kind":"symbol","identifier":"doc:\/\/com.expofp.sdk\/documentation\/ExpoFP\/ExpoFpSearchModel","navigatorTitle":[{"kind":"identifier","text":"ExpoFpSearchModel"}],"abstract":[{"type":"text","text":"Search model with info about an item"}],"type":"topic","fragments":[{"kind":"keyword","text":"struct"},{"kind":"text","text":" "},{"kind":"identifier","text":"ExpoFpSearchModel"}],"url":"\/documentation\/expofp\/expofpsearchmodel","title":"ExpoFpSearchModel"},"doc://com.expofp.sdk/documentation/ExpoFP/Listen-Plan-events":{"identifier":"doc:\/\/com.expofp.sdk\/documentation\/ExpoFP\/Listen-Plan-events","role":"article","abstract":[{"text":"Listen and respond to user interactions with the plan.","type":"text"}],"kind":"article","url":"\/documentation\/expofp\/listen-plan-events","type":"topic","title":"Listen Plan events"},"doc://com.expofp.sdk/documentation/ExpoFP/ExpoFpElementsVisibility":{"url":"\/documentation\/expofp\/expofpelementsvisibility","type":"topic","abstract":[{"text":"Elements visibility in a plan","type":"text"}],"kind":"symbol","navigatorTitle":[{"text":"ExpoFpElementsVisibility","kind":"identifier"}],"title":"ExpoFpElementsVisibility","fragments":[{"text":"struct","kind":"keyword"},{"text":" ","kind":"text"},{"text":"ExpoFpElementsVisibility","kind":"identifier"}],"identifier":"doc:\/\/com.expofp.sdk\/documentation\/ExpoFP\/ExpoFpElementsVisibility","role":"symbol"},"doc://com.expofp.sdk/documentation/ExpoFP/ExpoFpConsoleMessage":{"title":"ExpoFpConsoleMessage","type":"topic","navigatorTitle":[{"kind":"identifier","text":"ExpoFpConsoleMessage"}],"identifier":"doc:\/\/com.expofp.sdk\/documentation\/ExpoFP\/ExpoFpConsoleMessage","role":"symbol","kind":"symbol","url":"\/documentation\/expofp\/expofpconsolemessage","fragments":[{"kind":"keyword","text":"struct"},{"kind":"text","text":" "},{"kind":"identifier","text":"ExpoFpConsoleMessage"}],"abstract":[{"type":"text","text":"Information about "},{"code":"console","type":"codeVoice"},{"type":"text","text":" output"}]},"doc://com.expofp.sdk/documentation/ExpoFP/Manage-properties-and-settings":{"abstract":[{"text":"Reload a plan with new settings, apply, change or remove current settings and check the plan loading status.","type":"text"}],"role":"article","kind":"article","title":"Manage properties and settings","url":"\/documentation\/expofp\/manage-properties-and-settings","type":"topic","identifier":"doc:\/\/com.expofp.sdk\/documentation\/ExpoFP\/Manage-properties-and-settings"},"doc://com.expofp.sdk/documentation/ExpoFP/ExpoFpDirection":{"abstract":[{"text":"Information about the built route","type":"text"}],"url":"\/documentation\/expofp\/expofpdirection","kind":"symbol","fragments":[{"text":"struct","kind":"keyword"},{"text":" ","kind":"text"},{"text":"ExpoFpDirection","kind":"identifier"}],"identifier":"doc:\/\/com.expofp.sdk\/documentation\/ExpoFP\/ExpoFpDirection","navigatorTitle":[{"text":"ExpoFpDirection","kind":"identifier"}],"title":"ExpoFpDirection","role":"symbol","type":"topic"},"doc://com.expofp.sdk/documentation/ExpoFP/ExpoFpPlanPreloader":{"title":"ExpoFpPlanPreloader","abstract":[{"type":"text","text":"Loader for preloading plans."}],"kind":"symbol","navigatorTitle":[{"text":"ExpoFpPlanPreloader","kind":"identifier"}],"fragments":[{"text":"struct","kind":"keyword"},{"text":" ","kind":"text"},{"text":"ExpoFpPlanPreloader","kind":"identifier"}],"url":"\/documentation\/expofp\/expofpplanpreloader","role":"symbol","type":"topic","identifier":"doc:\/\/com.expofp.sdk\/documentation\/ExpoFP\/ExpoFpPlanPreloader"},"doc://com.expofp.sdk/documentation/ExpoFP/ExpoFpCategory":{"navigatorTitle":[{"text":"ExpoFpCategory","kind":"identifier"}],"title":"ExpoFpCategory","type":"topic","identifier":"doc:\/\/com.expofp.sdk\/documentation\/ExpoFP\/ExpoFpCategory","url":"\/documentation\/expofp\/expofpcategory","kind":"symbol","role":"symbol","abstract":[{"text":"Category info","type":"text"}],"fragments":[{"text":"struct","kind":"keyword"},{"text":" ","kind":"text"},{"text":"ExpoFpCategory","kind":"identifier"}]},"doc://com.expofp.sdk/documentation/ExpoFP/ExpoFpLine":{"title":"ExpoFpLine","abstract":[{"text":"Line on floor plan","type":"text"}],"identifier":"doc:\/\/com.expofp.sdk\/documentation\/ExpoFP\/ExpoFpLine","role":"symbol","kind":"symbol","navigatorTitle":[{"text":"ExpoFpLine","kind":"identifier"}],"url":"\/documentation\/expofp\/expofpline","fragments":[{"text":"struct","kind":"keyword"},{"text":" ","kind":"text"},{"text":"ExpoFpLine","kind":"identifier"}],"type":"topic"},"doc://com.expofp.sdk/documentation/ExpoFP/Setup-navigation":{"type":"topic","identifier":"doc:\/\/com.expofp.sdk\/documentation\/ExpoFP\/Setup-navigation","title":"Setup navigation","abstract":[{"text":"Setup your own location provider or use one of our pertners and help people navigate in a plan.","type":"text"}],"kind":"article","role":"article","url":"\/documentation\/expofp\/setup-navigation"},"doc://com.expofp.sdk/documentation/ExpoFP/ExpoFpDownloadedPlanInfo":{"type":"topic","kind":"symbol","title":"ExpoFpDownloadedPlanInfo","identifier":"doc:\/\/com.expofp.sdk\/documentation\/ExpoFP\/ExpoFpDownloadedPlanInfo","abstract":[{"text":"Information about the saved plan in the cache directory.","type":"text"}],"url":"\/documentation\/expofp\/expofpdownloadedplaninfo","role":"symbol","fragments":[{"text":"struct","kind":"keyword"},{"text":" ","kind":"text"},{"text":"ExpoFpDownloadedPlanInfo","kind":"identifier"}],"navigatorTitle":[{"text":"ExpoFpDownloadedPlanInfo","kind":"identifier"}]},"doc://com.expofp.sdk/documentation/ExpoFP/ExpoFpBoothClickEvent":{"identifier":"doc:\/\/com.expofp.sdk\/documentation\/ExpoFP\/ExpoFpBoothClickEvent","navigatorTitle":[{"text":"ExpoFpBoothClickEvent","kind":"identifier"}],"abstract":[{"type":"text","text":"Booth click event info"}],"url":"\/documentation\/expofp\/expofpboothclickevent","title":"ExpoFpBoothClickEvent","kind":"symbol","role":"symbol","type":"topic","fragments":[{"text":"struct","kind":"keyword"},{"text":" ","kind":"text"},{"text":"ExpoFpBoothClickEvent","kind":"identifier"}]},"doc://com.expofp.sdk/documentation/ExpoFP/ExpoFpRouteWaypoint":{"navigatorTitle":[{"text":"ExpoFpRouteWaypoint","kind":"identifier"}],"url":"\/documentation\/expofp\/expofproutewaypoint","identifier":"doc:\/\/com.expofp.sdk\/documentation\/ExpoFP\/ExpoFpRouteWaypoint","title":"ExpoFpRouteWaypoint","fragments":[{"text":"enum","kind":"keyword"},{"text":" ","kind":"text"},{"text":"ExpoFpRouteWaypoint","kind":"identifier"}],"kind":"symbol","type":"topic","role":"symbol","abstract":[{"type":"text","text":"Route waypoint booth name or current position"}]},"doc://com.expofp.sdk/documentation/ExpoFP/Migration-guide-from-v4-to-v5":{"abstract":[{"type":"text","text":"How to easily migrate SDK from version 4 to version 5 and start using new features."}],"type":"topic","title":"Migration guide from v4 to v5","kind":"article","url":"\/documentation\/expofp\/migration-guide-from-v4-to-v5","identifier":"doc:\/\/com.expofp.sdk\/documentation\/ExpoFP\/Migration-guide-from-v4-to-v5","role":"article"},"doc://com.expofp.sdk/documentation/ExpoFP/ExpoFpResult":{"url":"\/documentation\/expofp\/expofpresult","identifier":"doc:\/\/com.expofp.sdk\/documentation\/ExpoFP\/ExpoFpResult","abstract":[{"text":"A value that represents either a success or a failure after command execution.","type":"text"}],"kind":"symbol","type":"topic","role":"symbol","title":"ExpoFpResult","fragments":[{"text":"typealias","kind":"keyword"},{"text":" ","kind":"text"},{"text":"ExpoFpResult","kind":"identifier"}],"navigatorTitle":[{"text":"ExpoFpResult","kind":"identifier"}]},"https://blog.cocoapods.org/CocoaPods-Specs-Repo/":{"titleInlineContent":[{"text":"will be deprecated soon","type":"text"}],"type":"link","url":"https:\/\/blog.cocoapods.org\/CocoaPods-Specs-Repo\/","identifier":"https:\/\/blog.cocoapods.org\/CocoaPods-Specs-Repo\/","title":"will be deprecated soon"},"doc://com.expofp.sdk/documentation/ExpoFP/ExpoFpError":{"title":"ExpoFpError","abstract":[{"text":"An error that representing a cause of SDK failure.","type":"text"}],"identifier":"doc:\/\/com.expofp.sdk\/documentation\/ExpoFP\/ExpoFpError","role":"symbol","url":"\/documentation\/expofp\/expofperror","kind":"symbol","navigatorTitle":[{"text":"ExpoFpError","kind":"identifier"}],"type":"topic","fragments":[{"text":"enum","kind":"keyword"},{"text":" ","kind":"text"},{"kind":"identifier","text":"ExpoFpError"}]},"doc://com.expofp.sdk/documentation/ExpoFP/ExpoFpPlanDownloader":{"identifier":"doc:\/\/com.expofp.sdk\/documentation\/ExpoFP\/ExpoFpPlanDownloader","kind":"symbol","title":"ExpoFpPlanDownloader","role":"symbol","fragments":[{"kind":"keyword","text":"struct"},{"kind":"text","text":" "},{"kind":"identifier","text":"ExpoFpPlanDownloader"}],"type":"topic","navigatorTitle":[{"kind":"identifier","text":"ExpoFpPlanDownloader"}],"url":"\/documentation\/expofp\/expofpplandownloader","abstract":[{"type":"text","text":"Loader for downloading and savind plans in the cache directory."}]},"doc://com.expofp.sdk/documentation/ExpoFP/ExpoFpUnknownSearchItem":{"fragments":[{"text":"struct","kind":"keyword"},{"text":" ","kind":"text"},{"text":"ExpoFpUnknownSearchItem","kind":"identifier"}],"url":"\/documentation\/expofp\/expofpunknownsearchitem","role":"symbol","type":"topic","kind":"symbol","identifier":"doc:\/\/com.expofp.sdk\/documentation\/ExpoFP\/ExpoFpUnknownSearchItem","abstract":[{"type":"text","text":"Unsupported item"}],"title":"ExpoFpUnknownSearchItem","navigatorTitle":[{"text":"ExpoFpUnknownSearchItem","kind":"identifier"}]},"doc://com.expofp.sdk/documentation/ExpoFP/IExpoFpPlanPresenter":{"title":"IExpoFpPlanPresenter","fragments":[{"text":"protocol","kind":"keyword"},{"text":" ","kind":"text"},{"text":"IExpoFpPlanPresenter","kind":"identifier"}],"abstract":[{"type":"text","text":"Presenter for managing a specific plan."}],"role":"symbol","navigatorTitle":[{"text":"IExpoFpPlanPresenter","kind":"identifier"}],"kind":"symbol","type":"topic","identifier":"doc:\/\/com.expofp.sdk\/documentation\/ExpoFP\/IExpoFpPlanPresenter","url":"\/documentation\/expofp\/iexpofpplanpresenter"},"doc://com.expofp.sdk/documentation/ExpoFP/Manage-Plan":{"abstract":[{"type":"text","text":"Apply commands and request information from a plan via "},{"type":"codeVoice","code":"presenter"},{"type":"text","text":"."}],"identifier":"doc:\/\/com.expofp.sdk\/documentation\/ExpoFP\/Manage-Plan","kind":"article","role":"article","type":"topic","title":"Manage Plan","url":"\/documentation\/expofp\/manage-plan"}}}